MANIFEST.in
README.rst
requirements.txt
setup.cfg
setup.py
neuro_evolution/__init__.py
neuro_evolution/_config.py
neuro_evolution/_neat.py
neuro_evolution/_nsga_sort.py
neuro_evolution/_version.py
neuro_evolution/_wann.py
neuro_evolution/_wann_genes.py
neuro_evolution/_wann_genome.py
neuro_evolution/_wann_reproduce.py
neuro_evolution/visualization.py
neuro_evolution/tests/__init__.py
neuro_evolution/tests/test_neat.py
neuro_evolution/tests/test_wann.py
sklearn_neuro_evolution.egg-info/PKG-INFO
sklearn_neuro_evolution.egg-info/SOURCES.txt
sklearn_neuro_evolution.egg-info/dependency_links.txt
sklearn_neuro_evolution.egg-info/not-zip-safe
sklearn_neuro_evolution.egg-info/requires.txt
sklearn_neuro_evolution.egg-info/top_level.txt