Metadata-Version: 2.1
Name: sklearn-neuro-evolution
Version: 1.2.2
Summary: scikit-learn compatible package for neuro evolution.
Home-page: https://github.com/MarkoMlakar/sklearn-neuro-evolution
Maintainer: M. Mlakar
Maintainer-email: markomlakar2@gmail.com
License: new BSD
Download-URL: https://github.com/MarkoMlakar/sklearn-neuro-evolution/releases/tag/v1.2.2
Platform: UNKNOWN
Classifier: Intended Audience :: Science/Research
Classifier: Intended Audience :: Developers
Classifier: License :: OSI Approved
Classifier: Programming Language :: Python
Classifier: Topic :: Software Development
Classifier: Topic :: Scientific/Engineering
Classifier: Operating System :: Microsoft :: Windows
Classifier: Operating System :: POSIX
Classifier: Operating System :: Unix
Classifier: Operating System :: MacOS
Classifier: Programming Language :: Python :: 2.7
Classifier: Programming Language :: Python :: 3.5
Classifier: Programming Language :: Python :: 3.6
Classifier: Programming Language :: Python :: 3.7
Provides-Extra: tests
Provides-Extra: docs
